orange_mcp_server/__init__.py
orange_mcp_server-0.1.0.dist-info/WHEEL
orange_mcp_server-0.1.0.dist-info/entry_points.txt
orange_mcp_server-0.1.0.dist-info/METADATA
orange_mcp_server-0.1.0.dist-info/RECORD
