Metadata-Version: 2.3
Name: orange-mcp-server
Version: 0.1.0
Summary: Add your description here
Author: wufc
Author-email: wufc <wu_fucheng8@163.com>
Requires-Dist: mcp[cli]>=1.26.0
Requires-Python: >=3.14
